git_boss/__init__.py
git_boss/__main__.py
git_boss/config.default.yaml
git_boss/config.py
git_boss/git.py
git_boss/commands/__init__.py
git_boss/commands/add.py
git_boss/commands/grep.py
git_boss/commands/ls.py
git_boss/commands/remove.py
git_boss/commands/set_starting_folder.py
git_boss/commands/sync.py
git_boss/commands/version.py
git_boss-0.0.4.dist-info/licenses/LICENSE
git_boss-0.0.4.dist-info/METADATA
git_boss-0.0.4.dist-info/WHEEL
git_boss-0.0.4.dist-info/top_level.txt
git_boss-0.0.4.dist-info/RECORD
