Metadata-Version: 2.4
Name: git_boss
Version: 0.0.4
Summary: Python git project management tool
Author: kristof9851
Project-URL: Homepage, https://github.com/kristof9851/git_boss
Project-URL: Issues, https://github.com/kristof9851/git_boss/issues
Requires-Python: >=3.8
License-File: LICENSE
Requires-Dist: gitpython>=3.1.40
Requires-Dist: pytest>=7.4.3
Requires-Dist: pytest-mock>=3.12.0
Requires-Dist: PyYAML>=6.0
Dynamic: license-file
